{
    "currentStatus": "On active service",
    "constructNumber": "43295",
    "engineType": "Turbojet",
    "address": "Korea Republic of",
    "modelSICAO24Code": null,
    "manufacture": "Cessna",
    "deliveryDate": null,
    "name": "01-280",
    "seats": 2,
    "type": "Fixed wing multi engine",
    "owner": "Republic of Korea Air Force",
    "engineManufacture": "General Electric J85-GE-17A",
    "yearBuilt": "1970",
    "engines": 2,
    "alsoRegister": null,
    "registrationNumber": "01-280",
    "model": "A-37B Dragonfly    Search all Cessna A-37B Dragonfly"
}