{
    "currentStatus": "On display",
    "constructNumber": "150312",
    "engineType": "Turbojet",
    "address": "Horni NemciCzech Republic",
    "modelSICAO24Code": null,
    "manufacture": "Aero",
    "deliveryDate": null,
    "name": "0312",
    "seats": 1,
    "type": "Fixed wing multi engine",
    "owner": null,
    "engineManufacture": "Tumansky RD-9BF",
    "yearBuilt": "0000",
    "engines": 2,
    "alsoRegister": null,
    "registrationNumber": "0312",
    "model": "S-105 (MiG-19S)    Search all Aero S-105 (MiG-19S)"
}