{
    "currentStatus": "On active service",
    "constructNumber": "BB-924",
    "engineType": "Turbo-prop",
    "address": "United States",
    "modelSICAO24Code": null,
    "manufacture": "Beech",
    "deliveryDate": null,
    "name": "05-52305",
    "seats": 11,
    "type": "Fixed wing multi engine",
    "owner": null,
    "engineManufacture": "Pratt & Whitney Canada PT6A-42",
    "yearBuilt": "1981",
    "engines": 2,
    "alsoRegister": null,
    "registrationNumber": "05-52305",
    "model": "C-12C Huron    Search all Beech C-12C Huron"
}