{
    "currentStatus": "Withdrawn from service",
    "constructNumber": "421C0089",
    "engineType": "Reciprocating",
    "address": "Turkey",
    "modelSICAO24Code": null,
    "manufacture": "Cessna",
    "deliveryDate": "1977-02-00",
    "name": "10006",
    "seats": 0,
    "type": "Fixed wing multi engine",
    "owner": "Turkish Air Force (T\u00fcrk Hava Kuvvetleri)",
    "engineManufacture": null,
    "yearBuilt": "1976",
    "engines": 2,
    "alsoRegister": "TC-KAZ  De-registered\nN98783  De-registered  Delivery: 1976-06-28  Cancel: 1977-04-08",
    "registrationNumber": "10006",
    "model": "421C Golden Eagle    Search all Cessna 421C"
}