{
    "currentStatus": "Withdrawn from service",
    "constructNumber": "CL-66B-10",
    "engineType": "Reciprocating",
    "address": "Canada",
    "modelSICAO24Code": null,
    "manufacture": "Canadair",
    "deliveryDate": null,
    "name": "109160",
    "seats": 67,
    "type": "Fixed wing multi engine",
    "owner": "Canadian Armed Forces",
    "engineManufacture": "Allison 501-D36",
    "yearBuilt": "0000",
    "engines": 2,
    "alsoRegister": null,
    "registrationNumber": "109160",
    "model": "CC-109 Cosmopolitan    Search all Canadair CC-109 Cosmopolitan"
}