{
    "currentStatus": null,
    "constructNumber": "11007",
    "engineType": null,
    "address": "chile",
    "modelSICAO24Code": null,
    "manufacture": "Balloon Works",
    "deliveryDate": null,
    "name": "11006",
    "seats": 1,
    "type": null,
    "owner": "gabriel valenzuela v.",
    "engineManufacture": "None NONE",
    "yearBuilt": "1981",
    "engines": 0,
    "alsoRegister": "N1515X  Deregistered  Cancel: 2007-02-28",
    "registrationNumber": "11006",
    "model": "FIREFLY 7    Search all Balloon Works FIREFLY 7"
}