{
    "currentStatus": "On active service",
    "constructNumber": "Not found 14-00067",
    "engineType": "Turbo-prop",
    "address": "Redstone Arsenal Huntsville AlabamaUnited States",
    "modelSICAO24Code": null,
    "manufacture": "Beechcraft",
    "deliveryDate": null,
    "name": "14-00067",
    "seats": 2,
    "type": "Fixed wing single engine",
    "owner": "US Army Aviation Flight Test Directorate",
    "engineManufacture": "Pratt & Whitney Canada PT6A-68",
    "yearBuilt": "2015",
    "engines": 1,
    "alsoRegister": null,
    "registrationNumber": "14-00067",
    "model": "T-6D Texan II    Search all Beechcraft T-6D Texan II"
}