{
    "currentStatus": "Preserved",
    "constructNumber": "11143",
    "engineType": "Turbo-prop",
    "address": "TehranIran (Islamic Republic of)",
    "modelSICAO24Code": null,
    "manufacture": "Aero Commander",
    "deliveryDate": null,
    "name": "15-2238",
    "seats": 11,
    "type": "Fixed wing multi engine",
    "owner": "Islamic Republic of Iran Air Force",
    "engineManufacture": "AiResearch TPE331 SERIES",
    "yearBuilt": "1974",
    "engines": 2,
    "alsoRegister": "N57143  Deregistered  Cancel: 2010-10-26\nEP-AHL  De-registered",
    "registrationNumber": "15-2238",
    "model": "690A Turbo Commander    Search all Aero Commander 690A"
}