{
    "currentStatus": "Preserved",
    "constructNumber": "232",
    "engineType": "Turbojet",
    "address": "BordeauxFrance",
    "modelSICAO24Code": null,
    "manufacture": "Dassault",
    "deliveryDate": null,
    "name": "232",
    "seats": 1,
    "type": "Fixed wing single engine",
    "owner": "Conservatoire de l'Air et de l'Espace d'Aquitaine",
    "engineManufacture": "Rolls-Royce Nene 104B",
    "yearBuilt": "0000",
    "engines": 1,
    "alsoRegister": "F-GNYD  Registered",
    "registrationNumber": "232",
    "model": "MD-450 Ouragan    Search all Dassault MD-450 Ouragan"
}