{
    "currentStatus": "De-registered",
    "constructNumber": "180",
    "engineType": null,
    "address": "France",
    "modelSICAO24Code": null,
    "manufacture": "Brugger",
    "deliveryDate": "1998-12-11",
    "name": "27-MB",
    "seats": 1,
    "type": null,
    "owner": null,
    "engineManufacture": null,
    "yearBuilt": "0000",
    "engines": 1,
    "alsoRegister": "F-PYOI \n29-IA  Registered",
    "registrationNumber": "27-MB",
    "model": "MB-2 Colibri    Search all Brugger MB-2"
}