{
    "currentStatus": "De-registered",
    "constructNumber": "25254",
    "engineType": "Turbofan",
    "address": "Swaziland",
    "modelSICAO24Code": null,
    "manufacture": "Hawker Siddeley",
    "deliveryDate": null,
    "name": "3D-AVL",
    "seats": 0,
    "type": "Fixed wing multi engine",
    "owner": null,
    "engineManufacture": "Garrett AiResearch TFE731-3R",
    "yearBuilt": "1971",
    "engines": 2,
    "alsoRegister": "G-AYLG  De-registered\nG-VJAY  De-registered",
    "registrationNumber": "3D-AVL",
    "model": "HS.125 Series F400B    Search all Hawker Siddeley HS.125 Series F400B"
}