{
    "currentStatus": "On active service",
    "constructNumber": "382-5235",
    "engineType": "Turbo-prop",
    "address": "Prince Abdullah Air Base JeddahSaudi Arabia",
    "modelSICAO24Code": null,
    "manufacture": "Lockheed",
    "deliveryDate": null,
    "name": "473",
    "seats": 0,
    "type": "Fixed wing multi engine",
    "owner": "Royal Saudi Air Force",
    "engineManufacture": "Allison T56-A-15",
    "yearBuilt": "0000",
    "engines": 4,
    "alsoRegister": "N473MT  Registered  Delivery: 2015-02-24",
    "registrationNumber": "473",
    "model": "C-130H Hercules (L-382)    Search all Lockheed C-130H Hercules (L-382)"
}