{
    "currentStatus": "Registered",
    "constructNumber": "640",
    "engineType": "Reciprocating",
    "address": "Tel AvivIsrael",
    "modelSICAO24Code": null,
    "manufacture": "Britten-Norman",
    "deliveryDate": null,
    "name": "4X-CAY",
    "seats": 9,
    "type": "Fixed wing multi engine",
    "owner": "Nesher Aviation Tourism",
    "engineManufacture": "Lycoming O-540-E4C5",
    "yearBuilt": "1972",
    "engines": 2,
    "alsoRegister": "G-AYOC  De-registered\nCR-CAT  De-registered",
    "registrationNumber": "4X-CAY",
    "model": "BN-2A-8 Islander    Search all Britten-Norman BN-2A-8 Islander"
}