{
    "currentStatus": "Registered",
    "constructNumber": "41393",
    "engineType": "Turbo-shaft",
    "address": "Nigeria",
    "modelSICAO24Code": null,
    "manufacture": "AgustaWestland",
    "deliveryDate": null,
    "name": "5N-BSK",
    "seats": 15,
    "type": "Rotorcraft",
    "owner": "Caverton Helicopters",
    "engineManufacture": "Pratt & Whitney Canada PT6C-67C",
    "yearBuilt": "2014",
    "engines": 2,
    "alsoRegister": "N393SM  De-registered  Delivery: 2015-01-07  Cancel: 2015-12-16",
    "registrationNumber": "5N-BSK",
    "model": "AW-139    Search all AgustaWestland AW-139"
}