{
    "currentStatus": "On active service",
    "constructNumber": "312499",
    "engineType": "Turbo-prop",
    "address": "Mauritania",
    "modelSICAO24Code": null,
    "manufacture": "Embraer",
    "deliveryDate": null,
    "name": "5T-MAT",
    "seats": 2,
    "type": "Fixed wing single engine",
    "owner": "Force Aerienne Islamique de Mauritanie",
    "engineManufacture": "Pratt & Whitney Canada PT6A-25",
    "yearBuilt": "0000",
    "engines": 1,
    "alsoRegister": "499  To Mauretania",
    "registrationNumber": "5T-MAT",
    "model": "EMB-312F Tucano    Search all Embraer EMB-312F Tucano"
}