{
    "currentStatus": "preserved",
    "constructNumber": "12561",
    "engineType": "Turbojet",
    "address": "France",
    "modelSICAO24Code": null,
    "manufacture": "Douglas",
    "deliveryDate": null,
    "name": "928",
    "seats": 1,
    "type": "Fixed wing single engine",
    "owner": "Conservatoire de l'Air et de l'Espace d'Aquitaine",
    "engineManufacture": "Wright J65-W-20",
    "yearBuilt": "0000",
    "engines": 1,
    "alsoRegister": "147797  to RSiAF as 928",
    "registrationNumber": "928",
    "model": "A-4SU Skyhawk    Search all Douglas A-4SU Skyhawk"
}