{
    "currentStatus": "On active service",
    "constructNumber": "C133",
    "engineType": "Turbo-prop",
    "address": "Erkilet Air BaseTurkey",
    "modelSICAO24Code": null,
    "manufacture": "Airtech",
    "deliveryDate": null,
    "name": "97-133",
    "seats": 46,
    "type": "Fixed wing multi engine",
    "owner": "Turkish Air Force (T\u00fcrk Hava Kuvvetleri)",
    "engineManufacture": "General Electric CT7-9C",
    "yearBuilt": "0000",
    "engines": 2,
    "alsoRegister": null,
    "registrationNumber": "97-133",
    "model": "CN-235-100M    Search all Airtech CN-235-100M"
}