{
    "currentStatus": "Withdrawn from service",
    "constructNumber": "12807",
    "engineType": "Reciprocating",
    "address": "Australia",
    "modelSICAO24Code": null,
    "manufacture": "Bristol",
    "deliveryDate": null,
    "name": "A81-3",
    "seats": 0,
    "type": "Fixed wing multi engine",
    "owner": "Royal Australian Air Force",
    "engineManufacture": "Bristol Hercules 734",
    "yearBuilt": "1946",
    "engines": 2,
    "alsoRegister": "VH-SJG  Crashed on May 10, 1975\nG-AIMR  De-registered  Delivery: 1946-12-03",
    "registrationNumber": "A81-3",
    "model": "170 Freighter Mk.21E    Search all Bristol 170 Freighter Mk.21E"
}