{
    "currentStatus": "Registered",
    "constructNumber": "291",
    "engineType": "Reciprocating",
    "address": "North Gower Ontario K0A2T0Canada",
    "modelSICAO24Code": "C00A3B",
    "manufacture": "Aeronca",
    "deliveryDate": "1998-09-21",
    "name": "C-FDWS",
    "seats": 0,
    "type": null,
    "owner": null,
    "engineManufacture": null,
    "yearBuilt": "1998",
    "engines": 1,
    "alsoRegister": null,
    "registrationNumber": "C-FDWS",
    "model": "L-16 Replica    Search all Aeronca L-16 Replica"
}