{
    "currentStatus": "De-registered",
    "constructNumber": "7CCM-201",
    "engineType": "Reciprocating",
    "address": "Atikokan Ontario P0T 1C0Canada",
    "modelSICAO24Code": "C00CEF",
    "manufacture": "Aeronca",
    "deliveryDate": "2017-06-15",
    "name": "C-FEXI",
    "seats": 3,
    "type": "Fixed wing single engine",
    "owner": "John Torbiak",
    "engineManufacture": "Cont Motor C90 SERIES",
    "yearBuilt": "1948",
    "engines": 1,
    "alsoRegister": "N5556J  Valid",
    "registrationNumber": "C-FEXI",
    "model": "7CCM    Search all Aeronca 7CCM"
}