{
    "currentStatus": "Registered",
    "constructNumber": "15ACX 195X",
    "engineType": "Reciprocating",
    "address": "Forest Grove British Columbia V0K1M0Canada",
    "modelSICAO24Code": "C00BB2",
    "manufacture": "Aeronca",
    "deliveryDate": "1987-12-08",
    "name": "C-FELD",
    "seats": 0,
    "type": null,
    "owner": null,
    "engineManufacture": null,
    "yearBuilt": "1948",
    "engines": 1,
    "alsoRegister": null,
    "registrationNumber": "C-FELD",
    "model": "Sedan    Search all Aeronca Sedan"
}