{
    "currentStatus": "De-registered",
    "constructNumber": "62070",
    "engineType": "Turbo-shaft",
    "address": "Vancouve British Columbia V7B 1A5Canada",
    "modelSICAO24Code": "C00BBD",
    "manufacture": "Sikorsky",
    "deliveryDate": "1998-03-04",
    "name": "C-FELO",
    "seats": 20,
    "type": "Rotorcraft",
    "owner": "Okanagan Helicopters Limited",
    "engineManufacture": "General Electric T58-GE-8",
    "yearBuilt": "0000",
    "engines": 1,
    "alsoRegister": null,
    "registrationNumber": "C-FELO",
    "model": "S-62A    Search all Sikorsky S-62A"
}