{
    "currentStatus": "Registered",
    "constructNumber": "214 70",
    "engineType": "Reciprocating",
    "address": "Bracebridge Ontario P1L1X2Canada",
    "modelSICAO24Code": "C00F10",
    "manufacture": "Champion",
    "deliveryDate": "2001-06-04",
    "name": "C-FFSH",
    "seats": 0,
    "type": null,
    "owner": null,
    "engineManufacture": null,
    "yearBuilt": "1970",
    "engines": 1,
    "alsoRegister": null,
    "registrationNumber": "C-FFSH",
    "model": "7GCBC    Search all Champion 7GCBC"
}