{
    "currentStatus": "Registered",
    "constructNumber": "15AC-123",
    "engineType": "Reciprocating",
    "address": "Prince George British Columbia V2N4T5Canada",
    "modelSICAO24Code": "C00F94",
    "manufacture": "Aeronca",
    "deliveryDate": "1986-08-07",
    "name": "C-FFXJ",
    "seats": 0,
    "type": null,
    "owner": null,
    "engineManufacture": null,
    "yearBuilt": "1948",
    "engines": 1,
    "alsoRegister": null,
    "registrationNumber": "C-FFXJ",
    "model": "15AC Sedan    Search all Aeronca 15AC"
}