{
    "currentStatus": "De-registered",
    "constructNumber": "680-535-204",
    "engineType": "Reciprocating",
    "address": "Ottawa Ontario K1G 3N3Canada",
    "modelSICAO24Code": "C00D37",
    "manufacture": "Aero Commander",
    "deliveryDate": "2006-09-15",
    "name": "C-FFAC",
    "seats": 7,
    "type": "Fixed wing multi engine",
    "owner": "Survair Ltd",
    "engineManufacture": "Continental IO-360-C/D",
    "yearBuilt": "1957",
    "engines": 2,
    "alsoRegister": "N1333  Deregistered  Cancel: 1965-03-31",
    "registrationNumber": "C-FFAC",
    "model": "680    Search all Aero Commander 680"
}