{
    "currentStatus": "Registered",
    "constructNumber": "90C-3002",
    "engineType": null,
    "address": "Belmont Ontario N0L1B0Canada",
    "modelSICAO24Code": "C02235",
    "manufacture": "Aerostar",
    "deliveryDate": "1992-06-16",
    "name": "C-FMYU",
    "seats": 0,
    "type": null,
    "owner": "Labatt Brewing Company Limited",
    "engineManufacture": null,
    "yearBuilt": "1992",
    "engines": 0,
    "alsoRegister": null,
    "registrationNumber": "C-FMYU",
    "model": "90C    Search all Aerostar 90C"
}