{
    "currentStatus": "De-registered",
    "constructNumber": "27-239",
    "engineType": "Reciprocating",
    "address": "Slave Lake Alberta TQG 2AOCanada",
    "modelSICAO24Code": "C02F59",
    "manufacture": "Piper",
    "deliveryDate": "1999-08-16",
    "name": "C-FRYE",
    "seats": 6,
    "type": "Fixed wing multi engine",
    "owner": "Bayview Air Service Ltd",
    "engineManufacture": "Lycoming 0-540 SERIES",
    "yearBuilt": "1961",
    "engines": 2,
    "alsoRegister": "N2969G  Undel Tri",
    "registrationNumber": "C-FRYE",
    "model": "PA-23-250    Search all Piper PA-23-250"
}