{
    "currentStatus": "Registered",
    "constructNumber": "4018",
    "engineType": null,
    "address": "Trois-Rivi\u00e8res Quebec G8Z 2E7Canada",
    "modelSICAO24Code": null,
    "manufacture": "Cameron Balloons",
    "deliveryDate": "2017-07-12",
    "name": "C-FVSJ",
    "seats": 0,
    "type": "Balloon",
    "owner": "Jacob Vaillancourt",
    "engineManufacture": null,
    "yearBuilt": "0000",
    "engines": 0,
    "alsoRegister": "PH-CAP  De-registered\nG-CIGK  De-registered  Delivery: 2014-05-28  Cancel: 2017-06-22",
    "registrationNumber": "C-FVSJ",
    "model": "N-133    Search all Cameron Balloons N-133"
}