{
    "currentStatus": "Registered",
    "constructNumber": "463",
    "engineType": "Reciprocating",
    "address": "Sudbury Ontario P3Q1K9Canada",
    "modelSICAO24Code": "C0420F",
    "manufacture": "Barrows",
    "deliveryDate": "2010-06-10",
    "name": "C-FZAK",
    "seats": 4,
    "type": null,
    "owner": null,
    "engineManufacture": null,
    "yearBuilt": "2010",
    "engines": 1,
    "alsoRegister": null,
    "registrationNumber": "C-FZAK",
    "model": "Bearhawk    Search all Barrows Bearhawk"
}