{
    "currentStatus": "Registered",
    "constructNumber": "3219",
    "engineType": "Reciprocating",
    "address": "Schomberg Ontario L0G1T0Canada",
    "modelSICAO24Code": "C046F1",
    "manufacture": "Cirrus",
    "deliveryDate": "2009-04-24",
    "name": "C-GAWM",
    "seats": 0,
    "type": null,
    "owner": null,
    "engineManufacture": null,
    "yearBuilt": "2009",
    "engines": 1,
    "alsoRegister": null,
    "registrationNumber": "C-GAWM",
    "model": "SR22    Search all Cirrus SR22"
}