{
    "currentStatus": "De-registered",
    "constructNumber": "AA5-0220",
    "engineType": "Reciprocating",
    "address": " OntarioCanada",
    "modelSICAO24Code": null,
    "manufacture": "American Aviation",
    "deliveryDate": "2016-06-03",
    "name": "C-GJDQ",
    "seats": 0,
    "type": "Rotorcraft",
    "owner": "Wendake H\u00e9licopt\u00e8re inc.",
    "engineManufacture": "Turbomeca Arrius 2B1",
    "yearBuilt": "1973",
    "engines": 1,
    "alsoRegister": "N995PT  Deregistered  Cancel: 2010-11-03\nN67AL  Registered  Delivery: 2018-04-24",
    "registrationNumber": "C-GJDQ",
    "model": "AA-5 Traveler    Search all American Aviation AA-5"
}