{
    "currentStatus": "Registered",
    "constructNumber": "7847",
    "engineType": null,
    "address": "Thunder Bay Ontario P7C5P3Canada",
    "modelSICAO24Code": "C07D38",
    "manufacture": "Balloon Works",
    "deliveryDate": "1985-05-29",
    "name": "C-GVKX",
    "seats": 0,
    "type": null,
    "owner": null,
    "engineManufacture": null,
    "yearBuilt": "1978",
    "engines": 0,
    "alsoRegister": null,
    "registrationNumber": "C-GVKX",
    "model": "FIREFLY 7    Search all Balloon Works FIREFLY 7"
}