{
    "currentStatus": "Registered",
    "constructNumber": "TC012406",
    "engineType": "Reciprocating",
    "address": "Quill Lake Saskatchewan S0A3E0Canada",
    "modelSICAO24Code": "C08BAC",
    "manufacture": "Birdman",
    "deliveryDate": "1988-10-03",
    "name": "C-IAXF",
    "seats": 1,
    "type": null,
    "owner": null,
    "engineManufacture": "CUYUNA 440 - CROSBY MFG. CO.",
    "yearBuilt": "1982",
    "engines": 1,
    "alsoRegister": null,
    "registrationNumber": "C-IAXF",
    "model": "ATLAS XC    Search all Birdman ATLAS XC"
}