{
    "currentStatus": "Registered",
    "constructNumber": "18",
    "engineType": "Reciprocating",
    "address": "Vermilion Alberta T0B4M0Canada",
    "modelSICAO24Code": "C08C9B",
    "manufacture": "Birdman",
    "deliveryDate": "1983-05-27",
    "name": "C-IBGK",
    "seats": 1,
    "type": null,
    "owner": null,
    "engineManufacture": "ROTAX SERIES",
    "yearBuilt": "1983",
    "engines": 1,
    "alsoRegister": null,
    "registrationNumber": "C-IBGK",
    "model": "CHINOOK WT II    Search all Birdman CHINOOK WT II"
}