{
    "currentStatus": null,
    "constructNumber": "0918200032",
    "engineType": "Reciprocating",
    "address": "Canada",
    "modelSICAO24Code": null,
    "manufacture": "Bushmaster",
    "deliveryDate": null,
    "name": "C-IDWG",
    "seats": 2,
    "type": null,
    "owner": null,
    "engineManufacture": "ROTAX SERIES",
    "yearBuilt": "1985",
    "engines": 1,
    "alsoRegister": null,
    "registrationNumber": "C-IDWG",
    "model": "Bushmaster II    Search all Bushmaster Bushmaster II"
}