{
    "currentStatus": "Registered",
    "constructNumber": "3623",
    "engineType": "Reciprocating",
    "address": "London Ontario N5W1V2Canada",
    "modelSICAO24Code": "C09722",
    "manufacture": "Coldfire",
    "deliveryDate": "1997-08-20",
    "name": "C-IFGB",
    "seats": 1,
    "type": null,
    "owner": null,
    "engineManufacture": "ROTAX SERIES",
    "yearBuilt": "1997",
    "engines": 1,
    "alsoRegister": null,
    "registrationNumber": "C-IFGB",
    "model": "Dream Machine 582    Search all Coldfire Dream Machine 582"
}