{
    "currentStatus": "Registered",
    "constructNumber": "3021",
    "engineType": "Reciprocating",
    "address": "Carlysle Saskatchewan S0C0R0Canada",
    "modelSICAO24Code": "C09AC0",
    "manufacture": "ASAP",
    "deliveryDate": "2001-05-15",
    "name": "C-IGPR",
    "seats": 2,
    "type": null,
    "owner": "Coffey Elk Ranch Ltd",
    "engineManufacture": "ZANZOTTERA",
    "yearBuilt": "2001",
    "engines": 1,
    "alsoRegister": null,
    "registrationNumber": "C-IGPR",
    "model": "SUMMIT 2    Search all ASAP SUMMIT 2"
}