{
    "currentStatus": "Registered",
    "constructNumber": "MK-522",
    "engineType": "Reciprocating",
    "address": "Nelson British Columbia V1L3K6Canada",
    "modelSICAO24Code": "C0A154",
    "manufacture": "Black Hawk",
    "deliveryDate": "2010-07-27",
    "name": "C-IJCL",
    "seats": 1,
    "type": null,
    "owner": null,
    "engineManufacture": "CORS-AIR",
    "yearBuilt": "2005",
    "engines": 1,
    "alsoRegister": null,
    "registrationNumber": "C-IJCL",
    "model": "172    Search all Black Hawk 172"
}