{
    "currentStatus": "Not Confirmed",
    "constructNumber": "2000",
    "engineType": "Reciprocating",
    "address": "",
    "modelSICAO24Code": null,
    "manufacture": "Morane-Saulnier",
    "deliveryDate": null,
    "name": "D-EARD",
    "seats": 4,
    "type": "Fixed wing single engine",
    "owner": "Transferred To Another Country Or Authority Oe",
    "engineManufacture": "Franklin 6A-350",
    "yearBuilt": "0000",
    "engines": 1,
    "alsoRegister": null,
    "registrationNumber": "D-EARD",
    "model": "MS.894A Rallye Minerva 220    Search all Morane-Saulnier MS.894A Rallye Minerva 220"
}