{
    "currentStatus": "De-registered",
    "constructNumber": "6",
    "engineType": "Reciprocating",
    "address": "France",
    "modelSICAO24Code": null,
    "manufacture": "Alpavia",
    "deliveryDate": null,
    "name": "F-BIUJ",
    "seats": 1,
    "type": "Fixed wing single engine",
    "owner": null,
    "engineManufacture": null,
    "yearBuilt": "0000",
    "engines": 1,
    "alsoRegister": "F-BLEM  De-registered\nF-CIUJ  Registered  Delivery: 2012-06-13",
    "registrationNumber": "F-BIUJ",
    "model": "Fournier RF-3    Search all Alpavia Fournier RF-3"
}