{
    "currentStatus": "Registered",
    "constructNumber": "888615",
    "engineType": "Reciprocating",
    "address": "France",
    "modelSICAO24Code": null,
    "manufacture": "Bacau",
    "deliveryDate": null,
    "name": "F-WRUF",
    "seats": 2,
    "type": "Fixed wing single engine",
    "owner": null,
    "engineManufacture": "Ivchenko Vedeneyev M-14P",
    "yearBuilt": "1988",
    "engines": 1,
    "alsoRegister": "57  De-registered,DOSAAF\nLY-AHF  De-registered\nRA-44472  De-registered\nG-CBLJ  De-registered  Delivery: 2002-04-19  Cancel: 2011-03-28",
    "registrationNumber": "F-WRUF",
    "model": "Yak-52    Search all Bacau Yak-52"
}