{
    "currentStatus": null,
    "constructNumber": "8",
    "engineType": null,
    "address": "United Kingdom",
    "modelSICAO24Code": null,
    "manufacture": "British Aircraft Manufacturing Company Ltd",
    "deliveryDate": null,
    "name": "G-ACOW",
    "seats": 0,
    "type": null,
    "owner": null,
    "engineManufacture": null,
    "yearBuilt": "0000",
    "engines": 1,
    "alsoRegister": null,
    "registrationNumber": "G-ACOW",
    "model": "BA Swallow 2    Search all British Aircraft Manufacturing Company Ltd BA Swallow 2"
}