{
    "currentStatus": "Permanently withdrawn from use",
    "constructNumber": "165",
    "engineType": "Reciprocating",
    "address": "United Kingdom",
    "modelSICAO24Code": null,
    "manufacture": "Brantly",
    "deliveryDate": "1962-05-30",
    "name": "G-ARZI",
    "seats": 0,
    "type": "Rotorcraft",
    "owner": null,
    "engineManufacture": "Lycoming VO-360-A1B",
    "yearBuilt": "1962",
    "engines": 1,
    "alsoRegister": null,
    "registrationNumber": "G-ARZI",
    "model": "B-2    Search all Brantly B-2"
}