{
    "currentStatus": "Registered",
    "constructNumber": "2255",
    "engineType": "Reciprocating",
    "address": "Rickmansworth WD3 6AWUnited Kingdom",
    "modelSICAO24Code": "402A98",
    "manufacture": "Aerotek",
    "deliveryDate": null,
    "name": "G-BOEM",
    "seats": 2,
    "type": "Fixed wing single engine",
    "owner": "M Murphy",
    "engineManufacture": "Lycoming AEIO-360-A1E",
    "yearBuilt": "1981",
    "engines": 1,
    "alsoRegister": "N31525  De-registered\nD-EKMM ",
    "registrationNumber": "G-BOEM",
    "model": "Pitts S-2A Special    Search all Aerotek Pitts S-2A"
}