{
    "currentStatus": "Registered",
    "constructNumber": "2031",
    "engineType": "Reciprocating",
    "address": "London N1 4NTUnited Kingdom",
    "modelSICAO24Code": "406CD9",
    "manufacture": "Alisport",
    "deliveryDate": "2014-10-08",
    "name": "G-CIKD",
    "seats": 1,
    "type": "Glider",
    "owner": "Bryan Norman Searle",
    "engineManufacture": null,
    "yearBuilt": "2008",
    "engines": 1,
    "alsoRegister": null,
    "registrationNumber": "G-CIKD",
    "model": "Silent 2 Targa    Search all Alisport Silent 2 Targa"
}