{
    "currentStatus": "Registered",
    "constructNumber": "110078BA",
    "engineType": "None",
    "address": "Gillingham Dorset SP8 5QPUnited Kingdom",
    "modelSICAO24Code": "40770B",
    "manufacture": "APCO Aviation",
    "deliveryDate": "2018-11-01",
    "name": "G-CLBR",
    "seats": 0,
    "type": "Fixed wing single engine",
    "owner": "Giles Benedict Nunez Cardozo",
    "engineManufacture": null,
    "yearBuilt": "2018",
    "engines": 1,
    "alsoRegister": null,
    "registrationNumber": "G-CLBR",
    "model": "Cruiser 500/Parajet Explorer    Search all APCO Aviation Cruiser 500/Parajet Explorer"
}