{
    "currentStatus": null,
    "constructNumber": "4169",
    "engineType": null,
    "address": "United Kingdom",
    "modelSICAO24Code": null,
    "manufacture": "American Aerolights Inc",
    "deliveryDate": null,
    "name": "G-MBJD",
    "seats": 0,
    "type": null,
    "owner": null,
    "engineManufacture": "ZENOAH G25B1",
    "yearBuilt": "1981",
    "engines": 1,
    "alsoRegister": null,
    "registrationNumber": "G-MBJD",
    "model": "EAGLE 215B    Search all American Aerolights Inc EAGLE 215B"
}