{
    "currentStatus": null,
    "constructNumber": "E3990",
    "engineType": null,
    "address": "United Kingdom",
    "modelSICAO24Code": null,
    "manufacture": "American Aerolights Inc",
    "deliveryDate": null,
    "name": "G-MBCE",
    "seats": 0,
    "type": null,
    "owner": null,
    "engineManufacture": "- --",
    "yearBuilt": "0000",
    "engines": 1,
    "alsoRegister": null,
    "registrationNumber": "G-MBCE",
    "model": "EAGLE 215B    Search all American Aerolights Inc EAGLE 215B"
}