{
    "currentStatus": null,
    "constructNumber": "130SX/315/MU-F013",
    "engineType": null,
    "address": "United Kingdom",
    "modelSICAO24Code": null,
    "manufacture": "Aerial Arts",
    "deliveryDate": null,
    "name": "G-MNUL",
    "seats": 0,
    "type": null,
    "owner": null,
    "engineManufacture": "ROTAX 277",
    "yearBuilt": "1986",
    "engines": 1,
    "alsoRegister": null,
    "registrationNumber": "G-MNUL",
    "model": "130SX/Firefly    Search all Aerial Arts 130SX/Firefly"
}