{
    "currentStatus": null,
    "constructNumber": "CH754",
    "engineType": "Reciprocating",
    "address": "United Kingdom",
    "modelSICAO24Code": null,
    "manufacture": "Aerial Arts",
    "deliveryDate": null,
    "name": "G-MVJK",
    "seats": 1,
    "type": "Weight-shift-control",
    "owner": null,
    "engineManufacture": "ROTAX 377",
    "yearBuilt": "1988",
    "engines": 1,
    "alsoRegister": null,
    "registrationNumber": "G-MVJK",
    "model": "CHASER S    Search all Aerial Arts CHASER S"
}