{
    "currentStatus": "De-registered",
    "constructNumber": "14803033",
    "engineType": "Reciprocating",
    "address": "Hungary",
    "modelSICAO24Code": null,
    "manufacture": "Arado",
    "deliveryDate": null,
    "name": "HA-MAH",
    "seats": 2,
    "type": "Fixed wing single engine",
    "owner": "MAL\u00c9V",
    "engineManufacture": "Hirth HM 504A-2",
    "yearBuilt": "0000",
    "engines": 1,
    "alsoRegister": "CCCP-62647  De-registered\nRA-62647  De-registered",
    "registrationNumber": "HA-MAH",
    "model": "Ar-79    Search all Arado Ar-79"
}