{
    "currentStatus": "De-registered",
    "constructNumber": "251",
    "engineType": "Reciprocating",
    "address": "Hungary Air ForceHungary",
    "modelSICAO24Code": null,
    "manufacture": "Bucker (Zlin)",
    "deliveryDate": null,
    "name": "I-201",
    "seats": 2,
    "type": "Fixed wing single engine",
    "owner": null,
    "engineManufacture": "Hirth HM 504A",
    "yearBuilt": "1948",
    "engines": 1,
    "alsoRegister": "HA-BUL  De-registered",
    "registrationNumber": "I-201",
    "model": "Z-381 (C-106) Bestmann    Search all Bucker (Zlin) Z-381 (C-106) Bestmann"
}