{
    "currentStatus": "On active service",
    "constructNumber": "0057",
    "engineType": "Turbo-shaft",
    "address": "China",
    "modelSICAO24Code": null,
    "manufacture": "Changhe",
    "deliveryDate": null,
    "name": "LH90467",
    "seats": 0,
    "type": "Rotorcraft",
    "owner": "People's Liberation Army Ground Force",
    "engineManufacture": null,
    "yearBuilt": "0000",
    "engines": 1,
    "alsoRegister": null,
    "registrationNumber": "LH90467",
    "model": "Z-11    Search all Changhe Z-11"
}