{
    "currentStatus": "Deregistered",
    "constructNumber": "31P7400226",
    "engineType": "Reciprocating",
    "address": "",
    "modelSICAO24Code": "A00535",
    "manufacture": "Piper",
    "deliveryDate": null,
    "name": "N100FD",
    "seats": 8,
    "type": "Fixed wing multi engine",
    "owner": "Freeman Decorating",
    "engineManufacture": "Lycoming TIGO-541-E1A",
    "yearBuilt": "0000",
    "engines": 2,
    "alsoRegister": null,
    "registrationNumber": "N100FD",
    "model": "PA-31P Navajo    Search all Piper PA-31P Navajo"
}