{
    "currentStatus": "Valid",
    "constructNumber": "6272",
    "engineType": "None",
    "address": "Shell Beach CA 93449United States",
    "modelSICAO24Code": "A00682",
    "manufacture": "Cameron Balloons Us",
    "deliveryDate": null,
    "name": "N100UM",
    "seats": 4,
    "type": "Balloon",
    "owner": null,
    "engineManufacture": "None NONE",
    "yearBuilt": "2000",
    "engines": 0,
    "alsoRegister": null,
    "registrationNumber": "N100UM",
    "model": "O-84    Search all Cameron Balloons Us O-84"
}