{
    "currentStatus": "Undel Tri",
    "constructNumber": "003",
    "engineType": "Turbo-prop",
    "address": "Ramey PR 00604",
    "modelSICAO24Code": "A00F9F",
    "manufacture": "Ahrens",
    "deliveryDate": null,
    "name": "N1028N",
    "seats": 29,
    "type": "Fixed wing multi engine",
    "owner": "Ahrens Acft Inc",
    "engineManufacture": null,
    "yearBuilt": "0000",
    "engines": 4,
    "alsoRegister": null,
    "registrationNumber": "N1028N",
    "model": "AR-404    Search all Ahrens AR-404"
}