{
    "currentStatus": "Deregistered",
    "constructNumber": "001 (N1053P)",
    "engineType": "None",
    "address": "Strasburg IL 62465United States",
    "modelSICAO24Code": "A01A16",
    "manufacture": "Bensen",
    "deliveryDate": null,
    "name": "N1053P",
    "seats": 1,
    "type": "Balloon",
    "owner": "Renaissance Balloons",
    "engineManufacture": "None NONE",
    "yearBuilt": "0000",
    "engines": 1,
    "alsoRegister": null,
    "registrationNumber": "N1053P",
    "model": "B-8M    Search all Bensen B-8M"
}