{
    "currentStatus": "Valid",
    "constructNumber": "116",
    "engineType": "Reciprocating",
    "address": "Eagle River AK 99577United States",
    "modelSICAO24Code": "A04415",
    "manufacture": "Aero Composites",
    "deliveryDate": null,
    "name": "N116SH",
    "seats": 2,
    "type": "Fixed wing single engine",
    "owner": null,
    "engineManufacture": "Lycoming 0-320 SERIES",
    "yearBuilt": "1989",
    "engines": 1,
    "alsoRegister": null,
    "registrationNumber": "N116SH",
    "model": "SEA HAWKER    Search all Aero Composites SEA HAWKER"
}