{
    "currentStatus": "Deregistered",
    "constructNumber": "5871",
    "engineType": "None",
    "address": "Strasburg OH 44680United States",
    "modelSICAO24Code": "A05055",
    "manufacture": "Cameron Balloons Us",
    "deliveryDate": null,
    "name": "N1192W",
    "seats": 4,
    "type": "Balloon",
    "owner": null,
    "engineManufacture": "None NONE",
    "yearBuilt": "1993",
    "engines": 0,
    "alsoRegister": null,
    "registrationNumber": "N1192W",
    "model": "N-90    Search all Cameron Balloons Us N-90"
}