{
    "currentStatus": "Deregistered",
    "constructNumber": "10097",
    "engineType": "Reciprocating",
    "address": "Rochester NH 03867",
    "modelSICAO24Code": "A050B8",
    "manufacture": "American General",
    "deliveryDate": null,
    "name": "N1195Q",
    "seats": 4,
    "type": "Fixed wing single engine",
    "owner": "SKYHAVEN ENTERPRISES INC",
    "engineManufacture": null,
    "yearBuilt": "0000",
    "engines": 1,
    "alsoRegister": null,
    "registrationNumber": "N1195Q",
    "model": "AG-5B Tiger    Search all American General AG-5B"
}