{
    "currentStatus": "Sale Reported",
    "constructNumber": "195",
    "engineType": "Reciprocating",
    "address": "Boise ID 83702United States",
    "modelSICAO24Code": "A059E0",
    "manufacture": "Buhl",
    "deliveryDate": null,
    "name": "N12106",
    "seats": 1,
    "type": "Fixed wing single engine",
    "owner": null,
    "engineManufacture": "Cont Motor A&C65 SERIES",
    "yearBuilt": "0000",
    "engines": 1,
    "alsoRegister": null,
    "registrationNumber": "N12106",
    "model": "LA-1    Search all Buhl LA-1"
}