{
    "currentStatus": "Deregistered",
    "constructNumber": "525-0464",
    "engineType": "Turbofan",
    "address": "Wichita KS 67201United States",
    "modelSICAO24Code": "A0745C",
    "manufacture": "Cessna",
    "deliveryDate": null,
    "name": "N1284P",
    "seats": 8,
    "type": "Fixed wing multi engine",
    "owner": "CESSNA AIRCRAFT COMPANY",
    "engineManufacture": "Williams FJ 44 SERIES",
    "yearBuilt": "2001",
    "engines": 2,
    "alsoRegister": "362  On active service  Delivery: 2001-11-13",
    "registrationNumber": "N1284P",
    "model": "525 CitationJet CJ1    Search all Cessna 525 CitationJet CJ1"
}