{
    "currentStatus": "Sale Reported",
    "constructNumber": "1",
    "engineType": "Reciprocating",
    "address": "Citrus Heughts CA 95610United States",
    "modelSICAO24Code": "A094AF",
    "manufacture": "Aerosport",
    "deliveryDate": null,
    "name": "N1366K",
    "seats": 2,
    "type": "Fixed wing single engine",
    "owner": null,
    "engineManufacture": "Cont Motor C85 SERIES",
    "yearBuilt": "1982",
    "engines": 1,
    "alsoRegister": null,
    "registrationNumber": "N1366K",
    "model": "Woody Pusher    Search all Aerosport Woody Pusher"
}