{
    "currentStatus": "In Question",
    "constructNumber": "5921",
    "engineType": "None",
    "address": "Shakopee MN 55379United States",
    "modelSICAO24Code": "A0F45C",
    "manufacture": "Cameron Balloons Us",
    "deliveryDate": null,
    "name": "N1602R",
    "seats": 4,
    "type": "Balloon",
    "owner": null,
    "engineManufacture": "None NONE",
    "yearBuilt": "1993",
    "engines": 0,
    "alsoRegister": null,
    "registrationNumber": "N1602R",
    "model": "N-90    Search all Cameron Balloons Us N-90"
}