{
    "currentStatus": "Valid",
    "constructNumber": "4561",
    "engineType": "Ramjet",
    "address": "Howard KS 67349United States",
    "modelSICAO24Code": "A106C7",
    "manufacture": "Buckeye",
    "deliveryDate": null,
    "name": "N1651L",
    "seats": 2,
    "type": "Powered Parachute",
    "owner": null,
    "engineManufacture": "Rotax 582",
    "yearBuilt": "1999",
    "engines": 1,
    "alsoRegister": null,
    "registrationNumber": "N1651L",
    "model": "BUCKEYE DREAM    Search all Buckeye BUCKEYE DREAM"
}