{
    "currentStatus": "Valid",
    "constructNumber": "12827",
    "engineType": "Turbojet",
    "address": "Dallas TX 75201United States",
    "modelSICAO24Code": "A1DB03",
    "manufacture": "Douglas",
    "deliveryDate": null,
    "name": "N219AT",
    "seats": 1,
    "type": "Fixed wing single engine",
    "owner": "Landstreet Investment Corp",
    "engineManufacture": "Wright J65-W-4",
    "yearBuilt": "0000",
    "engines": 1,
    "alsoRegister": "149502  Withdrawn from service",
    "registrationNumber": "N219AT",
    "model": "A4D-2N Skyhawk    Search all Douglas A4D-2N Skyhawk"
}