{
    "currentStatus": "Deregistered",
    "constructNumber": "1003",
    "engineType": "None",
    "address": "Yardley PA 19067",
    "modelSICAO24Code": "A1E8E1",
    "manufacture": "Aerotek",
    "deliveryDate": null,
    "name": "N222EP",
    "seats": 1,
    "type": "Glider",
    "owner": null,
    "engineManufacture": "None NONE",
    "yearBuilt": "0000",
    "engines": 1,
    "alsoRegister": null,
    "registrationNumber": "N222EP",
    "model": "Pitts S-1T Special    Search all Aerotek Pitts S-1T"
}