{
    "currentStatus": "Undel Tri",
    "constructNumber": "19",
    "engineType": "Reciprocating",
    "address": "Marina Del Rey CA 90292United States",
    "modelSICAO24Code": "A1EC9B",
    "manufacture": "Berkut",
    "deliveryDate": null,
    "name": "N223ES",
    "seats": 2,
    "type": "Fixed wing single engine",
    "owner": null,
    "engineManufacture": null,
    "yearBuilt": "0000",
    "engines": 1,
    "alsoRegister": null,
    "registrationNumber": "N223ES",
    "model": "540    Search all Berkut 540"
}