{
    "currentStatus": "Deregistered",
    "constructNumber": "712",
    "engineType": "Reciprocating",
    "address": "Oklahoma City OK 73125",
    "modelSICAO24Code": "A2A198",
    "manufacture": "American Eagle",
    "deliveryDate": null,
    "name": "N269N",
    "seats": 3,
    "type": "Fixed wing single engine",
    "owner": null,
    "engineManufacture": "Cont Motor W670 SERIES",
    "yearBuilt": "1930",
    "engines": 1,
    "alsoRegister": null,
    "registrationNumber": "N269N",
    "model": "101    Search all American Eagle 101"
}