{
    "currentStatus": "Undel Tri",
    "constructNumber": "135",
    "engineType": "Reciprocating",
    "address": "Camdenton MO 65020United States",
    "modelSICAO24Code": "A2A54F",
    "manufacture": "Callair",
    "deliveryDate": null,
    "name": "N27N",
    "seats": 2,
    "type": "Fixed wing single engine",
    "owner": null,
    "engineManufacture": "Lycoming 0-290 SERIES",
    "yearBuilt": "0000",
    "engines": 1,
    "alsoRegister": null,
    "registrationNumber": "N27N",
    "model": "A-2    Search all Callair A-2"
}