{
    "currentStatus": "Deregistered",
    "constructNumber": "4-1085",
    "engineType": "None",
    "address": "New Castle IN 47362",
    "modelSICAO24Code": "A2D8F4",
    "manufacture": "Piper",
    "deliveryDate": null,
    "name": "N28282",
    "seats": 2,
    "type": "Balloon",
    "owner": "AIR TRAVELERS CLUB",
    "engineManufacture": "None NONE",
    "yearBuilt": "1940",
    "engines": 1,
    "alsoRegister": null,
    "registrationNumber": "N28282",
    "model": "J4A    Search all Piper J4A"
}