{
    "currentStatus": "Deregistered",
    "constructNumber": "319",
    "engineType": "Turbo-prop",
    "address": "Hollywood CA 90028",
    "modelSICAO24Code": "A39633",
    "manufacture": "American Eagle",
    "deliveryDate": null,
    "name": "N330E",
    "seats": 3,
    "type": "Fixed wing multi engine",
    "owner": "Tactical Air Operations Inc",
    "engineManufacture": null,
    "yearBuilt": "0000",
    "engines": 1,
    "alsoRegister": null,
    "registrationNumber": "N330E",
    "model": "101    Search all American Eagle 101"
}