{
    "currentStatus": "Valid",
    "constructNumber": "00004",
    "engineType": "Reciprocating",
    "address": "Newport News VA 23608United States",
    "modelSICAO24Code": "A39B19",
    "manufacture": "American Sportscopter",
    "deliveryDate": null,
    "name": "N331SC",
    "seats": 1,
    "type": "Rotorcraft",
    "owner": "American Sportscopter International Inc",
    "engineManufacture": "Ama/expr UNKNOWN ENG",
    "yearBuilt": "1999",
    "engines": 1,
    "alsoRegister": null,
    "registrationNumber": "N331SC",
    "model": "ULTRASPORT 331    Search all American Sportscopter ULTRASPORT 331"
}