{
    "currentStatus": "Valid",
    "constructNumber": "157",
    "engineType": "Reciprocating",
    "address": "Rhome TX 76078United States",
    "modelSICAO24Code": "A42C2A",
    "manufacture": "Buhl",
    "deliveryDate": null,
    "name": "N368Y",
    "seats": 1,
    "type": "Fixed wing single engine",
    "owner": null,
    "engineManufacture": "Cont Motor A80 SERIES",
    "yearBuilt": "1931",
    "engines": 1,
    "alsoRegister": null,
    "registrationNumber": "N368Y",
    "model": "LA-1    Search all Buhl LA-1"
}