{
    "currentStatus": "Deregistered",
    "constructNumber": "5166",
    "engineType": "None",
    "address": "riverside C 92504",
    "modelSICAO24Code": "A4BA55",
    "manufacture": "Hiller",
    "deliveryDate": null,
    "name": "N4031V",
    "seats": 4,
    "type": "Balloon",
    "owner": ",CALIFORNIA AIRCRAFT SERVICE",
    "engineManufacture": "None NONE",
    "yearBuilt": "0000",
    "engines": 1,
    "alsoRegister": null,
    "registrationNumber": "N4031V",
    "model": "UH-12E    Search all Hiller UH-12E"
}