{
    "currentStatus": "Deregistered",
    "constructNumber": "2215",
    "engineType": "Reciprocating",
    "address": "Ensign KS 67841",
    "modelSICAO24Code": "A5D763",
    "manufacture": "Arrow",
    "deliveryDate": null,
    "name": "N476",
    "seats": 2,
    "type": "Fixed wing single engine",
    "owner": null,
    "engineManufacture": "Cont Motor C85 SERIES",
    "yearBuilt": "0000",
    "engines": 1,
    "alsoRegister": null,
    "registrationNumber": "N476",
    "model": "Sport    Search all Arrow Sport"
}