{
    "currentStatus": "Deregistered",
    "constructNumber": "04340",
    "engineType": "Reciprocating",
    "address": "Honolulu HI 96816",
    "modelSICAO24Code": "A629BC",
    "manufacture": "De Havilland",
    "deliveryDate": null,
    "name": "N4967N",
    "seats": 13,
    "type": "Fixed wing single engine",
    "owner": "BLUE SKY AIRLINES LTD",
    "engineManufacture": "Lycoming 0-320 SERIES",
    "yearBuilt": "0000",
    "engines": 2,
    "alsoRegister": null,
    "registrationNumber": "N4967N",
    "model": "DH-104 Dove 6A    Search all De Havilland DH-104 Dove 6A"
}