{
    "currentStatus": "Deregistered",
    "constructNumber": "0003",
    "engineType": null,
    "address": "Englewood CO 801124549United States",
    "modelSICAO24Code": "A64174",
    "manufacture": "Adam Aircraft",
    "deliveryDate": null,
    "name": "N502AX",
    "seats": 6,
    "type": null,
    "owner": "AAI ACQUISITION INC",
    "engineManufacture": "Cont Motor TSIO-550-E",
    "yearBuilt": "2003",
    "engines": 2,
    "alsoRegister": null,
    "registrationNumber": "N502AX",
    "model": "A500    Search all Adam Aircraft A500"
}