{
    "currentStatus": "Valid",
    "constructNumber": "B-259",
    "engineType": "Reciprocating",
    "address": "Astoria OR 97103United States",
    "modelSICAO24Code": "A6EE18",
    "manufacture": "Alon",
    "deliveryDate": null,
    "name": "N5459F",
    "seats": 2,
    "type": "Fixed wing single engine",
    "owner": null,
    "engineManufacture": "Cont Motor C90 SERIES",
    "yearBuilt": "1967",
    "engines": 1,
    "alsoRegister": null,
    "registrationNumber": "N5459F",
    "model": "A2A Aircoupe    Search all Alon A2A"
}