{
    "currentStatus": "Valid",
    "constructNumber": "SKR0412537",
    "engineType": null,
    "address": "Patten ME 04765United States",
    "modelSICAO24Code": "A72A35",
    "manufacture": "Aeros (Best Off)",
    "deliveryDate": null,
    "name": "N56068",
    "seats": 2,
    "type": "Fixed wing single engine",
    "owner": null,
    "engineManufacture": "Rotax 912S",
    "yearBuilt": "2005",
    "engines": 1,
    "alsoRegister": null,
    "registrationNumber": "N56068",
    "model": "Skyranger II    Search all Aeros (Best Off) Skyranger II"
}