{
    "currentStatus": "Valid",
    "constructNumber": "601-017S",
    "engineType": "Reciprocating",
    "address": "Summerfield NC 27358United States",
    "modelSICAO24Code": "A7CCD3",
    "manufacture": "AMD",
    "deliveryDate": null,
    "name": "N601VB",
    "seats": 2,
    "type": "Fixed wing single engine",
    "owner": null,
    "engineManufacture": "Cont Motor 0-200-A",
    "yearBuilt": "2006",
    "engines": 1,
    "alsoRegister": null,
    "registrationNumber": "N601VB",
    "model": "CH-601XL SLSA    Search all AMD CH-601XL SLSA"
}