{
    "currentStatus": "deregistered",
    "constructNumber": "18-26",
    "engineType": "Reciprocating",
    "address": "United States",
    "modelSICAO24Code": "A7F895",
    "manufacture": "Air & Space America Inc",
    "deliveryDate": null,
    "name": "N6120S",
    "seats": 2,
    "type": "Rotorcraft",
    "owner": null,
    "engineManufacture": "Lycoming O-360-A1D",
    "yearBuilt": "1965",
    "engines": 1,
    "alsoRegister": "D-HOBB  preserved",
    "registrationNumber": "N6120S",
    "model": "18A    Search all Air & Space America Inc 18A"
}