{
    "currentStatus": "De-registered",
    "constructNumber": "20700691",
    "engineType": "Reciprocating",
    "address": "United States",
    "modelSICAO24Code": "A80408",
    "manufacture": "Cessna",
    "deliveryDate": null,
    "name": "N61520",
    "seats": 6,
    "type": "Fixed wing single engine",
    "owner": null,
    "engineManufacture": "Ama/expr UNKNOWN ENG",
    "yearBuilt": "0000",
    "engines": 1,
    "alsoRegister": "F-GDJA \nN9460M  De-registered\nOO-HRC  De-registered\nYV-748C  Destroyed",
    "registrationNumber": "N61520",
    "model": "207A    Search all Cessna 207A"
}