{
    "currentStatus": "Undel Tri",
    "constructNumber": "160",
    "engineType": "None",
    "address": "Inglewood CA 90304United States",
    "modelSICAO24Code": "A91FF3",
    "manufacture": "Bowlus",
    "deliveryDate": null,
    "name": "N68724",
    "seats": 1,
    "type": "Glider",
    "owner": null,
    "engineManufacture": "None NONE",
    "yearBuilt": "1948",
    "engines": 0,
    "alsoRegister": null,
    "registrationNumber": "N68724",
    "model": "BA-100    Search all Bowlus BA-100"
}