{
    "currentStatus": "Valid",
    "constructNumber": "023",
    "engineType": "Reciprocating",
    "address": "Elkton KY 42220United States",
    "modelSICAO24Code": "A9A522",
    "manufacture": "Barrows",
    "deliveryDate": null,
    "name": "N720SF",
    "seats": 4,
    "type": "Fixed wing single engine",
    "owner": null,
    "engineManufacture": null,
    "yearBuilt": "0000",
    "engines": 1,
    "alsoRegister": null,
    "registrationNumber": "N720SF",
    "model": "Bearhawk    Search all Barrows Bearhawk"
}