{
    "currentStatus": "Valid",
    "constructNumber": "97-221",
    "engineType": "Reciprocating",
    "address": "Beaumont CA 92223United States",
    "modelSICAO24Code": "AB4397",
    "manufacture": "Adventure Air",
    "deliveryDate": null,
    "name": "N825BR",
    "seats": 4,
    "type": "Fixed wing single engine",
    "owner": null,
    "engineManufacture": null,
    "yearBuilt": "0000",
    "engines": 1,
    "alsoRegister": null,
    "registrationNumber": "N825BR",
    "model": "Adventurer 333    Search all Adventure Air Adventurer 333"
}