{
    "currentStatus": "Valid",
    "constructNumber": "141",
    "engineType": "Reciprocating",
    "address": "Lake Oswego OR 97034United States",
    "modelSICAO24Code": "ABCC10",
    "manufacture": "American Eagle",
    "deliveryDate": null,
    "name": "N85966",
    "seats": 3,
    "type": "Fixed wing single engine",
    "owner": "R H Lindsay & Assoc Inc",
    "engineManufacture": null,
    "yearBuilt": "0000",
    "engines": 1,
    "alsoRegister": null,
    "registrationNumber": "N85966",
    "model": "101    Search all American Eagle 101"
}