{
    "currentStatus": "Deregistered",
    "constructNumber": "4615",
    "engineType": "Reciprocating",
    "address": "Phoenix AZ 85000United States",
    "modelSICAO24Code": "ABE073",
    "manufacture": "Ableiter",
    "deliveryDate": null,
    "name": "N86429",
    "seats": 1,
    "type": "Rotorcraft",
    "owner": null,
    "engineManufacture": "Mcculloch 4318A&E/0-100",
    "yearBuilt": "1962",
    "engines": 1,
    "alsoRegister": null,
    "registrationNumber": "N86429",
    "model": "GREEN HORNET GYRO    Search all Ableiter GREEN HORNET GYRO"
}