{
    "currentStatus": "Valid",
    "constructNumber": "79",
    "engineType": "None",
    "address": "Refugio TX 78377United States",
    "modelSICAO24Code": "AD3E90",
    "manufacture": "Briegleb",
    "deliveryDate": null,
    "name": "N9521",
    "seats": 1,
    "type": "Glider",
    "owner": null,
    "engineManufacture": "Ama/expr UNKNOWN ENG",
    "yearBuilt": "1970",
    "engines": 0,
    "alsoRegister": null,
    "registrationNumber": "N9521",
    "model": "BG-12BD    Search all Briegleb BG-12BD"
}