{
    "currentStatus": "Valid",
    "constructNumber": "101",
    "engineType": "None",
    "address": "Goshen NY 10924United States",
    "modelSICAO24Code": "AD83D9",
    "manufacture": "Cassidy Ronald",
    "deliveryDate": null,
    "name": "N970CB",
    "seats": 1,
    "type": "Balloon",
    "owner": "Blaser Swisslube Inc",
    "engineManufacture": "None NONE",
    "yearBuilt": "2005",
    "engines": 0,
    "alsoRegister": null,
    "registrationNumber": "N970CB",
    "model": "1666    Search all Cassidy Ronald 1666"
}