{
    "currentStatus": "De-registered",
    "constructNumber": "1196",
    "engineType": "None",
    "address": "Belgium",
    "modelSICAO24Code": null,
    "manufacture": "Colt",
    "deliveryDate": "2013-07-29",
    "name": "OO-BTH",
    "seats": 0,
    "type": "Balloon",
    "owner": "KWS Benelux",
    "engineManufacture": null,
    "yearBuilt": "1988",
    "engines": 0,
    "alsoRegister": "PH-WEK  De-registered",
    "registrationNumber": "OO-BTH",
    "model": "21A    Search all Colt 21A"
}