{
    "currentStatus": null,
    "constructNumber": "146",
    "engineType": "Reciprocating",
    "address": " NSWAustralia",
    "modelSICAO24Code": null,
    "manufacture": "Airparts Nz Ltd",
    "deliveryDate": null,
    "name": "VH-EQC",
    "seats": 0,
    "type": null,
    "owner": null,
    "engineManufacture": "Textron Lycoming IO-720",
    "yearBuilt": "1969",
    "engines": 1,
    "alsoRegister": null,
    "registrationNumber": "VH-EQC",
    "model": "FU-24/A4    Search all Airparts Nz Ltd FU-24/A4"
}